cloudmon/__init__.py
cloudmon/queue.py
cloudmon/connector/__init__.py
cloudmon/connector/base.py
cloudmon/connector/cache.py
cloudmon/connector/cloudstack.py
cloudmon/connector/cloudstack_queue.py
cloudmon/connector/ec2.py
cloudmon/connector/ec2_queue.py
cloudmon/connector/errors.py
cloudmon/connector/metrics.py
cloudmon/connector/proxy_queue.py
cloudmon/connector/zabbix.py
cloudmon/utils/__init__.py
cloudmon/utils/config.py
cloudmon/utils/log.py
cloudmon/utils/parse.py
cloudmon/utils/schema.py
cloudmon/utils/zabbix_macros.py
cloudmon-0.3.0.data/data/share/cloudmon/LICENSE
cloudmon-0.3.0.data/scripts/cloudmon
cloudmon-0.3.0.dist-info/METADATA
cloudmon-0.3.0.dist-info/RECORD
cloudmon-0.3.0.dist-info/WHEEL
cloudmon-0.3.0.dist-info/top_level.txt
etc/cloudmon/cloudmon.conf
etc/init.d/cloudmon
