Metadata-Version: 2.1
Name: cloudmon
Version: 0.3.0
Summary: Monitoring Orchestrator for Clouds
Home-page: https://github.com/globocom/cloudmon
Author: Adolfo Suzzano
Author-email: adolfo@ngxlabs.com
License: MIT license
Keywords: cloudmon
Platform: UNKNOWN
Classifier: Programming Language :: Python
Classifier: Programming Language :: Python :: 2
Classifier: Programming Language :: Python :: 2.7
Requires-Python: >=2.7, !=3.*
Requires-Dist: setuptools
Requires-Dist: cs
Requires-Dist: configobj
Requires-Dist: Cerberus
Requires-Dist: Unidecode
Requires-Dist: pika
Requires-Dist: python-daemon
Requires-Dist: pyzmq
Requires-Dist: pyzabbix
Requires-Dist: redis
Requires-Dist: boto3
